a_pandas_ex_reg2df/README.MD
a_pandas_ex_reg2df/__init__.py
a_pandas_ex_reg2df/requirements.txt
a_pandas_ex_reg2df/thirdparty.json
a_pandas_ex_reg2df-0.11.dist-info/LICENSE.rst
a_pandas_ex_reg2df-0.11.dist-info/METADATA
a_pandas_ex_reg2df-0.11.dist-info/WHEEL
a_pandas_ex_reg2df-0.11.dist-info/top_level.txt
a_pandas_ex_reg2df-0.11.dist-info/RECORD
